pyalko/__init__.py
pyalko/client.py
pyalko/const.py
pyalko/exceptions.py
pyalko/objects/__init__.py
pyalko/objects/base.py
pyalko/objects/device.py
pyalko-0.3.2.dist-info/METADATA
pyalko-0.3.2.dist-info/WHEEL
pyalko-0.3.2.dist-info/RECORD
