Metadata-Version: 2.3
Name: pyalko
Version: 0.3.2
Summary: Asynchronous python client for AL-KO Robolinho Mowers.
License: MIT
Keywords: alko,al-ko,robolinho,api,async,client
Author: Jon Kristian Nilsen
Author-email: hello@jonkristian.no
Requires-Python: >=3.8,<4.0
Classifier: License :: OSI Approved :: MIT License
Classifier: Programming Language :: Python :: 3
Classifier: Programming Language :: Python :: 3.8
Classifier: Programming Language :: Python :: 3.9
Classifier: Programming Language :: Python :: 3.10
Classifier: Programming Language :: Python :: 3.11
Classifier: Programming Language :: Python :: 3.12
Classifier: Programming Language :: Python :: 3.13
Requires-Dist: aiohttp (>=3.7.4,<4.0.0)
Project-URL: Documentation, https://github.com/jonkristian/pyalko
Project-URL: Homepage, https://github.com/jonkristian/pyalko
Project-URL: Repository, https://github.com/jonkristian/pyalko
